{"expireTime":9007200867124449000,"key":"create-remote-file-node-headers-https://scontent-del1-1.cdninstagram.com/v/t51.2885-15/e35/54513567_276585659909520_5920366703502240372_n.jpg?_nc_ht=scontent-del1-1.cdninstagram.com&_nc_cat=100&_nc_ohc=aS02Yf3pXGMAX_TuJrG&tp=1&oh=bc6c0bb5223e3642f1e2135233d0ade9&oe=6043AD30","val":{"last-modified":"Wed, 27 Mar 2019 11:37:54 GMT","x-haystack-needlechecksum":"1855775271","x-needle-checksum":"2480563753","content-type":"image/jpeg","x-content-id":"276585659909520","x-fb-config-version-olb-prod":"1008","timing-allow-origin":"*","cross-origin-resource-policy":"cross-origin","access-control-allow-origin":"*","cache-control":"max-age=1209600, no-transform","x-fb-trip-id":"1425083115","date":"Wed, 03 Feb 2021 20:17:38 GMT","alt-svc":"h3-29=\":443\"; ma=3600,h3-27=\":443\"; ma=3600","connection":"close","content-length":"33390"}}